mt2publ/__init__.py
mt2publ/__main__.py
mt2publ/__version__.py
mt2publ/category.py
mt2publ/entry.py
mt2publ/model.py
mt2publ-0.1.1.dist-info/LICENSE
mt2publ-0.1.1.dist-info/METADATA
mt2publ-0.1.1.dist-info/WHEEL
mt2publ-0.1.1.dist-info/entry_points.txt
mt2publ-0.1.1.dist-info/top_level.txt
mt2publ-0.1.1.dist-info/RECORD
